CHANGELOG.md
MANIFEST.in
README.md
setup.cfg
setup.py
rattail_nationbuilder/__init__.py
rattail_nationbuilder/_version.py
rattail_nationbuilder/app.py
rattail_nationbuilder/commands.py
rattail_nationbuilder/config.py
rattail_nationbuilder.egg-info/PKG-INFO
rattail_nationbuilder.egg-info/SOURCES.txt
rattail_nationbuilder.egg-info/dependency_links.txt
rattail_nationbuilder.egg-info/entry_points.txt
rattail_nationbuilder.egg-info/requires.txt
rattail_nationbuilder.egg-info/top_level.txt
rattail_nationbuilder/db/__init__.py
rattail_nationbuilder/db/alembic/versions/1e17031c4b3e_first_cache_tables.py
rattail_nationbuilder/db/alembic/versions/7fc3dee0e9c5_fix_nullable.py
rattail_nationbuilder/db/alembic/versions/c3cb75afcae2_add_donations_cache_table.py
rattail_nationbuilder/db/model/__init__.py
rattail_nationbuilder/db/model/nationbuilder.py
rattail_nationbuilder/importing/__init__.py
rattail_nationbuilder/importing/model.py
rattail_nationbuilder/importing/nationbuilder.py
rattail_nationbuilder/importing/versions.py
rattail_nationbuilder/nationbuilder/__init__.py
rattail_nationbuilder/nationbuilder/util.py
rattail_nationbuilder/nationbuilder/webapi.py