Metadata-Version: 2.1
Name: rattail-nationbuilder
Version: 0.1.12
Summary: Rattail integration package for NationBuilder
Home-page: https://rattailproject.org/
Author: Lance Edgar
Author-email: lance@edbob.org
License: GNU GPL v3
Classifier: Development Status :: 4 - Beta
Classifier: Intended Audience :: Developers
Classifier: License :: OSI Approved :: GNU General Public License v3 or later (GPLv3+)
Classifier: Natural Language :: English
Classifier: Operating System :: OS Independent
Classifier: Programming Language :: Python
Classifier: Programming Language :: Python :: 3
Classifier: Topic :: Office/Business
Classifier: Topic :: Software Development :: Libraries :: Python Modules
Requires-Dist: rattail
